gitbump.py
gitbump-1.0.7.dist-info/LICENSE.txt
gitbump-1.0.7.dist-info/METADATA
gitbump-1.0.7.dist-info/WHEEL
gitbump-1.0.7.dist-info/entry_points.txt
gitbump-1.0.7.dist-info/top_level.txt
gitbump-1.0.7.dist-info/RECORD
