Metadata-Version: 2.1
Name: gitbump
Version: 1.0.7
Summary: Git tags version automation
Home-page: https://gitlab.com/w00/gitbump
Author: Lukasz Kwiek
Author-email: lukasz.kwiek@ericsson.com
License: MIT
Platform: UNKNOWN
Classifier: Development Status :: 3 - Alpha
Classifier: Intended Audience :: Developers
Classifier: Topic :: Software Development :: Build Tools
Classifier: License :: OSI Approved :: MIT License
Classifier: Programming Language :: Python :: 3
Classifier: Programming Language :: Python :: 3.5
Requires-Dist: semver (==2.8.1)
